{"songs": [{"title": "Dear Prudence", "album": "The Beatles (The White Album)", "year": "1968-11-22", "lyrics": "Dear Prudence, won't you come out to play?\nDear Prudence, greet the brand new day, hey\nThe sun is up, the sky is blue\nIt's beautiful, and so are you\nDear Prudence, won't you come out to play?\n\nDear Prudence, open up your eyes\nDear Prudence, see the sunny skies\nThe wind is low, the birds will sing\nThat you are part of everything\nDear Prudence, won't you open up your eyes?\n\nLook around, round, round\nLook around, round, round\nLook around\n\nDear Prudence, let me see you smile\nDear Prudence, like a little child\nThe clouds will be a daisy chain\nSo let me see you smile again\nDear Prudence, won't you let me see you smile?\n\nDear Prudence, won't you come out to play?\nDear Prudence, greet the brand new day\nThe sun is up, the sky is blue\nIt's beautiful, and so are you\nDear Prudence, won't you come out to play?", "image": "https://images.genius.com/6862fc86bdaf0ab3e409a6f46cc20c9b.1000x1000x1.png"}], "artist": "The Beatles"}